AlPyVision/Data.py
AlPyVision/Runner.py
AlPyVision/Vision.py
AlPyVision/__init__.py
AlPyVision/UnitTest/UnitTest.py
AlPyVision/UnitTest/__init__.py
UnitTest/UnitTest.py
UnitTest/__init__.py
alpyvision-0.0.93.dist-info/LICENSE
alpyvision-0.0.93.dist-info/METADATA
alpyvision-0.0.93.dist-info/WHEEL
alpyvision-0.0.93.dist-info/top_level.txt
alpyvision-0.0.93.dist-info/RECORD
