Metadata-Version: 2.1
Name: alpyvision
Version: 0.0.93
Summary: AlPyVision is a Python wrapper to work with openCV and the Albion Online game client.
Home-page: https://github.com/MadMowgli/AlPyVision
Author: Joel Läubin
Author-email: laeubin.j@protonmail.com
License: MIT
Keywords: albion,opencv,computer vision
Platform: UNKNOWN
Classifier: Development Status :: 2 - Pre-Alpha
Classifier: Intended Audience :: Developers
Classifier: Intended Audience :: Education
Classifier: Topic :: Scientific/Engineering :: Visualization
Classifier: Topic :: Scientific/Engineering :: Image Recognition
Classifier: Topic :: Scientific/Engineering :: Image Processing
Classifier: Topic :: Multimedia :: Graphics :: Capture :: Screen Capture
Classifier: Programming Language :: Python :: 3
Classifier: Operating System :: Microsoft :: Windows
License-File: LICENSE
Requires-Dist: opencv-python
Requires-Dist: numpy
Requires-Dist: pywin32
